saml2/__init__.py
saml2/algsupport.py
saml2/argtree.py
saml2/assertion.py
saml2/attribute_converter.py
saml2/attribute_resolver.py
saml2/attributemaps/__init__.py
saml2/attributemaps/adfs_v1x.py
saml2/attributemaps/adfs_v20.py
saml2/attributemaps/basic.py
saml2/attributemaps/saml_uri.py
saml2/attributemaps/shibboleth_uri.py
saml2/authn.py
saml2/authn_context/__init__.py
saml2/authn_context/ippword.py
saml2/authn_context/mobiletwofactor.py
saml2/authn_context/ppt.py
saml2/authn_context/pword.py
saml2/authn_context/sslcert.py
saml2/authn_context/timesync.py
saml2/cache.py
saml2/cert.py
saml2/client.py
saml2/client_base.py
saml2/config.py
saml2/country_codes.py
saml2/cryptography/__init__.py
saml2/cryptography/asymmetric.py
saml2/cryptography/errors.py
saml2/cryptography/pki.py
saml2/cryptography/symmetric.py
saml2/data/__init__.py
saml2/data/schemas/__init__.py
saml2/data/schemas/eidas-schema-attribute-legalperson.xsd
saml2/data/schemas/eidas-schema-attribute-naturalperson.xsd
saml2/data/schemas/eidas-schema-metadata-servicelist.xsd
saml2/data/schemas/eidas-schema-saml-extensions.xsd
saml2/data/schemas/envelope.xsd
saml2/data/schemas/saml-schema-assertion-2.0.xsd
saml2/data/schemas/saml-schema-authn-context-2.0.xsd
saml2/data/schemas/saml-schema-authn-context-auth-telephony-2.0.xsd
saml2/data/schemas/saml-schema-authn-context-ip-2.0.xsd
saml2/data/schemas/saml-schema-authn-context-ippword-2.0.xsd
saml2/data/schemas/saml-schema-authn-context-kerberos-2.0.xsd
saml2/data/schemas/saml-schema-authn-context-mobileonefactor-reg-2.0.xsd
saml2/data/schemas/saml-schema-authn-context-mobileonefactor-unreg-2.0.xsd
saml2/data/schemas/saml-schema-authn-context-mobiletwofactor-reg-2.0.xsd
saml2/data/schemas/saml-schema-authn-context-mobiletwofactor-unreg-2.0.xsd
saml2/data/schemas/saml-schema-authn-context-nomad-telephony-2.0.xsd
saml2/data/schemas/saml-schema-authn-context-personal-telephony-2.0.xsd
saml2/data/schemas/saml-schema-authn-context-pgp-2.0.xsd
pysaml2_ams-7.5.5.dist-info/LICENSE
pysaml2_ams-7.5.5.dist-info/METADATA
pysaml2_ams-7.5.5.dist-info/WHEEL
pysaml2_ams-7.5.5.dist-info/entry_points.txt
pysaml2_ams-7.5.5.dist-info/RECORD
