Metadata-Version: 2.3
Name: pysaml2-ams
Version: 7.5.5
Summary: Python implementation of SAML Version 2 Standard
License: Apache-2.0
Keywords: saml,saml2,standard,federation,identity,idpy,IdentityPython
Author: IdentityPython
Author-email: discuss@idpy.org
Maintainer: IdentityPython
Maintainer-email: discuss@idpy.org
Requires-Python: >= 3.10
Classifier: Topic :: Software Development :: Libraries :: Python Modules
Provides-Extra: s2repoze
Requires-Dist: cryptography (>=3.1)
Requires-Dist: defusedxml
Requires-Dist: paste ; extra == "s2repoze"
Requires-Dist: pyopenssl
Requires-Dist: python-dateutil
Requires-Dist: repoze.who ; extra == "s2repoze"
Requires-Dist: requests (>=2.0.0,<3.0.0)
Requires-Dist: xmlschema (>=2.0.0,<3.0.0)
Requires-Dist: zope.interface ; extra == "s2repoze"
Project-URL: Changelog, https://github.com/IdentityPython/pysaml2/blob/master/CHANGELOG.md
Project-URL: Documentation, https://pysaml2.readthedocs.io
Project-URL: Homepage, https://idpy.org
Project-URL: Issues, https://github.com/IdentityPython/pysaml2/issues
Project-URL: Repository, https://github.com/IdentityPython/pysaml2
